{
	"class" : {
		"additionsToViewerCategories" : "sw 10/3/2004 01:34",
		"exampleBackgroundField" : "sw 6/13/2001 22:46" },
	"instance" : {
		"basicType" : "tk 11/1/2001 14:37",
		"configureForKids" : "sw 10/2/97 15:16",
		"couldHoldSeparateDataForEachInstance" : "sw 10/30/2000 09:02",
		"currentDataValue" : "sw 10/30/2000 09:01",
		"getNumericValue" : "sw 9/15/2000 06:14",
		"newContents:fromCard:" : "sw 5/31/2000 01:18",
		"setNewContentsFrom:" : "nice 12/27/2009 20:31",
		"setNumericValue:" : "sw 9/1/2000 10:44",
		"variableDocks" : "sw 10/25/2000 07:02" } }
